trustee/__init__.py
trustee/_version.py
trustee/enums/__init__.py
trustee/enums/feature_type.py
trustee/main.py
trustee/report/__init__.py
trustee/report/plot.py
trustee/report/trust.py
trustee/utils/__init__.py
trustee/utils/const.py
trustee/utils/dataset.py
trustee/utils/log.py
trustee/utils/persist.py
trustee/utils/plot.py
trustee/utils/rootpath.py
trustee/utils/tree.py
trustee-1.1.6.dist-info/LICENSE
trustee-1.1.6.dist-info/WHEEL
trustee-1.1.6.dist-info/METADATA
trustee-1.1.6.dist-info/RECORD
